pypasswordgen/src/__init__.py
pypasswordgen/src/pypasswordgen.py
pypasswordgen-1.0.1.dist-info/entry_points.txt
pypasswordgen-1.0.1.dist-info/LICENSE
pypasswordgen-1.0.1.dist-info/WHEEL
pypasswordgen-1.0.1.dist-info/METADATA
pypasswordgen-1.0.1.dist-info/RECORD
