Metadata-Version: 2.1
Name: pypasswordgen
Version: 1.0.1
Summary: A python based random password generator
Home-page: https://github.com/Arslan909/pypasswordgen
License: WTFPL
Keywords: password,generator,random
Author: Muhammad Arslan
Author-email: Arslanswl909@gmail.com
Requires-Python: >=3.10,<4.0
Classifier: License :: Other/Proprietary License
Classifier: Programming Language :: Python :: 3
Classifier: Programming Language :: Python :: 3.10
